movielensapi__sdk/__init__.py
movielensapi__sdk/film_client.py
movielensapi__sdk/film_config.py
movielensapi__sdk/schemas/__init__.py
movielensapi__sdk/schemas/schemas.py
movielensapi_sdk-0.0.2.dist-info/METADATA
movielensapi_sdk-0.0.2.dist-info/WHEEL
movielensapi_sdk-0.0.2.dist-info/top_level.txt
movielensapi_sdk-0.0.2.dist-info/RECORD
